{
    "timestamp": "2025-01-09 23:15:09",
    "news": [
        {
            "title": "Jawatankuasa perbankan Senat akan melancarkan subjawatan crypto pertama, mungkin dipimpin oleh Sen. Lummis.",
            "url": "https://cryptopanic.com/news/click/20529521/"
        },
        {
            "title": "Coinbase disaman oleh CFTC dalam siasatan Polymarket, memberi amaran kepada pengguna melalui emel.",
            "url": "https://cryptopanic.com/news/click/20529514/"
        },
        {
            "title": "ETH Mengalami Pengurangan Leverage Tetapi Pengumpulan Mungkin Meningkat",
            "url": "https://cryptopanic.com/news/click/20529519/"
        },
        {
            "title": "Binance Menambah Sokongan untuk Penjenamaan Mines of Dalarnia Dar Open Network (D)",
            "url": "https://cryptopanic.com/news/click/20529492/"
        },
        {
            "title": "Permainan DeFi Minggu Ini: Perdagangan Pendle",
            "url": "https://cryptopanic.com/news/click/20529493/"
        },
        {
            "title": "Lummis bersedia untuk mengetuai subkomite aset digital Senat yang baru ditubuhkan.",
            "url": "https://cryptopanic.com/news/click/20529478/"
        },
        {
            "title": "Polymarket diserang kerana pertaruhan pasaran kebakaran hutan California.",
            "url": "https://cryptopanic.com/news/click/20529476/"
        },
        {
            "title": "Jika Anda Melabur $1,000 Dalam Token XRP Ketika Bill Clinton Berucap Di Konferens Ripple, Inilah Berapa Banyak Yang Anda Miliki Hari Ini.",
            "url": "https://cryptopanic.com/news/click/20529475/"
        },
        {
            "title": "Saya tidak tahu.",
            "url": "https://cryptopanic.com/news/click/20529459/"
        },
        {
            "title": "Harga XRP bersedia untuk 'gerakan kuat' di atas $2.90 apabila metrik sentimen menunjukkan optimisme.",
            "url": "https://cryptopanic.com/news/click/20529442/"
        },
        {
            "title": "Rancangan Bandar Mindfulness Gelephu di Bhutan untuk Mewujudkan Rizab Kripto Strategik",
            "url": "https://cryptopanic.com/news/click/20529453/"
        },
        {
            "title": "Wakil Bryan Steil Dilantik sebagai Pengerusi Subkomite Aset Digital oleh French Hill dari Jawatankuasa Perkhidmatan Kewangan Dewan.",
            "url": "https://cryptopanic.com/news/click/20529444/"
        },
        {
            "title": "Ambisi Kripto Thailand Menghadapi Halangan Ketika Percubaan Pembayaran Phuket Menanti",
            "url": "https://cryptopanic.com/news/click/20529426/"
        },
        {
            "title": "Quant Crypto Sasarkan $429 Sebagai Peluang Kenaikan Walaupun Terdapat Penurunan Baru-baru Ini",
            "url": "https://cryptopanic.com/news/click/20529395/"
        },
        {
            "title": "TERKINI: Biden Musnahkan Rizab Bitcoin Strategik Amerika!",
            "url": "https://cryptopanic.com/news/click/20529410/"
        },
        {
            "title": "Langkah BESAR Bitcoin Seterusnya! Bersama Bitcoin Shooter, Sue Ennis dan Tom Honzik",
            "url": "https://cryptopanic.com/news/click/20529413/"
        },
        {
            "title": "Carta Kitaran Pasaran Sejarah Cadangkan Larian Bull Kripto Mungkin Akan Berterusan Sehingga 2026",
            "url": "https://cryptopanic.com/news/click/20529417/"
        },
        {
            "title": "Bolehkah harga Bitcoin jatuh lagi?",
            "url": "https://cryptopanic.com/news/click/20529344/"
        },
        {
            "title": "Akan kah Amazon & Microsoft Beli Bitcoin?!",
            "url": "https://cryptopanic.com/news/click/20529389/"
        },
        {
            "title": "Kajian Menunjukkan 22% Penasihat Kewangan Mengagihkan Kripto kepada Klien pada 2024, 56% Lebih Kemungkinan Selepas Pilihan Raya",
            "url": "https://cryptopanic.com/news/click/20529443/"
        }
    ]
}