{
    "timestamp": "2025-01-12 14:12:32",
    "news": [
        {
            "title": "'Tether Menguasai Hasil Yuran Crypto dengan $122M dalam Seminggu'",
            "url": "https://cryptopanic.com/news/click/20539554/"
        },
        {
            "title": "Harga Bitcoin ke $140,000 atau $67,000? Penganalisis Mengulas Tentang Persediaan BTC yang Menarik.",
            "url": "https://cryptopanic.com/news/click/20539562/"
        },
        {
            "title": "'Bitcoin Sedang Diserang - Bagaimana BlackRock Boleh Mengubahnya SELAMANYA'",
            "url": "https://cryptopanic.com/news/click/20539557/"
        },
        {
            "title": "Harga XLM mungkin bersedia untuk kenaikan 30% - Semua yang anda perlu tahu!",
            "url": "https://cryptopanic.com/news/click/20539544/"
        },
        {
            "title": "\"Donald Trump dan Xi Jinping menjadi kawan mungkin boleh mendatangkan masalah kepada ekonomi global.\"",
            "url": "https://cryptopanic.com/news/click/20539519/"
        },
        {
            "title": "\"Bursa kripto India Mudrex menjelaskan mengenai penghentian pengeluaran kripto\"",
            "url": "https://cryptopanic.com/news/click/20539518/"
        },
        {
            "title": "Paus Kumpul Doge Sementara Penganalisis Ubah Sasaran Harga Jangka Panjang Kepada $8 Menjelang 2028.",
            "url": "https://cryptopanic.com/news/click/20539520/"
        },
        {
            "title": "'Jumlah Perdagangan Altcoin di Binance Mencapai 78% Ketika Pakar Meramalkan Pasaran Bull 2025'",
            "url": "https://cryptopanic.com/news/click/20539510/"
        },
        {
            "title": "'Cardano (ADA) Melebihi Semua 10 Koin Teratas Ketika Ia Kembali kepada $1'",
            "url": "https://cryptopanic.com/news/click/20539494/"
        },
        {
            "title": "Adakah 2025 Tahun Crypto x Ejen AI?",
            "url": "https://cryptopanic.com/news/click/20539481/"
        },
        {
            "title": "'Kripto Pulih, Singularity Pisang Akan Datang, Binance Senaraikan Syiling AI'",
            "url": "https://cryptopanic.com/news/click/20539495/"
        },
        {
            "title": "Saya tidak tahu.",
            "url": "https://cryptopanic.com/news/click/20539449/"
        },
        {
            "title": "'ONDO menghadapi penurunan 17% yang mungkin – Adakah ini masa untuk membeli altcoin?'",
            "url": "https://cryptopanic.com/news/click/20539436/"
        },
        {
            "title": "Panduan Tips 'Zoo': Cara untuk Mengumpul Token Paling Banyak Sebelum Airdrop Permainan Telegram.",
            "url": "https://cryptopanic.com/news/click/20539424/"
        },
        {
            "title": "'Fantom Meningkat Ketika Rantaian Sonic Mencapai Pencapaian $100J'",
            "url": "https://cryptopanic.com/news/click/20539426/"
        },
        {
            "title": "Adakah Warren Buffett Bersedia Menyelamatkan Wall Street Dari Diri Sendiri? Sejarah Menunjukkan Apa yang Mungkin Dilakukan Oleh Legenda Billionaire Dengan Wang Tunai Rekod $325 Bilion.",
            "url": "https://cryptopanic.com/news/click/20539420/"
        },
        {
            "title": "Peniaga yang Tidak Tahu dan Menghindari Bitcoin Mempunyai Pandangan 'Bencana' Terhadap Pasaran, Kata Tom Lee dari Fundstrat.",
            "url": "https://cryptopanic.com/news/click/20539411/"
        },
        {
            "title": "Penganalisis Kata Lebih Banyak Akan Datang Apabila Harga Uniswap Pulih 5% Dalam Sebuah Hari.",
            "url": "https://cryptopanic.com/news/click/20539395/"
        },
        {
            "title": "'Polymarket Dilaporkan Diblok di Singapura, Menambah Cabaran Peraturan Global'",
            "url": "https://cryptopanic.com/news/click/20539471/"
        },
        {
            "title": "'Peter Brandt memuji XRP selepas lonjakan besar 10%'",
            "url": "https://cryptopanic.com/news/click/20539390/"
        }
    ]
}