{
    "timestamp": "2025-01-11 01:08:22",
    "news": [
        {
            "title": "Billionaire Melabur ~$1,777,000,000 Dalam Tiga Aset Dalam Pembaharuan Portfolio Besar: Laporan",
            "url": "https://cryptopanic.com/news/click/20534933/"
        },
        {
            "title": "\"Pedagang Mencatat 16,564% Dalam Jumlah Keuntungan di Altcoin AI Berasaskan Solana Dalam Tempoh Kurang Tiga Bulan: Data Dalam Rantaian\"",
            "url": "https://cryptopanic.com/news/click/20534920/"
        },
        {
            "title": "Messari memberhentikan kira-kira 15% kakitangan di tengah pemotongan dalam industri, disahkan oleh CEO Turner.",
            "url": "https://cryptopanic.com/news/click/20534896/"
        },
        {
            "title": "Pihak pengawal selia AS mencadangkan perlindungan yang lebih kuat terhadap penipuan pembayaran kripto dan pengawasan.",
            "url": "https://cryptopanic.com/news/click/20534888/"
        },
        {
            "title": "'North Dakota Pertimbangkan Rizab Kripto ketika Perbendaharaan Bitcoin Negeri Meningkat'",
            "url": "https://cryptopanic.com/news/click/20534813/"
        },
        {
            "title": "Standard token bersatu untuk memudahkan ekosistem Bitcoin yang terpecah.",
            "url": "https://cryptopanic.com/news/click/20534814/"
        },
        {
            "title": "Jerman meneroka penggunaan Bitcoin untuk menguatkan daya saing mata wang digital.",
            "url": "https://cryptopanic.com/news/click/20534755/"
        },
        {
            "title": "Ahli undang-undang North Dakota dorong untuk menambah Bitcoin ke dalam perbendaharaan negeri.",
            "url": "https://cryptopanic.com/news/click/20534736/"
        },
        {
            "title": "'Penggunaan XRP oleh Bank Of America: Kesan, Ramalan Harga'",
            "url": "https://cryptopanic.com/news/click/20534737/"
        },
        {
            "title": "Harga XRP Kekal Stabil Sementara Volume Dagangan Menurun 33%",
            "url": "https://cryptopanic.com/news/click/20534877/"
        },
        {
            "title": "Harga Ethereum Mungkin Melonjak Menuju $6,000 Ketika Ia Mengikuti Pola Teknikal Utama",
            "url": "https://cryptopanic.com/news/click/20534728/"
        },
        {
            "title": "Ahli undang-undang AS dedahkan pegangan BTC, XRP dan SOLnya.",
            "url": "https://cryptopanic.com/news/click/20534708/"
        },
        {
            "title": "Pengerusi SEC Gary Gensler berkata kes crypto telah mengganggu fikirannya, berpendapat D.O.G.E Elon Musk tidak perlu.",
            "url": "https://cryptopanic.com/news/click/20534707/"
        },
        {
            "title": "\"Asia mendahului dengan 60% pengguna crypto dunia, menurut Indeks Penerimaan Crypto Global 2024.\"",
            "url": "https://cryptopanic.com/news/click/20534682/"
        },
        {
            "title": "Tuduhan terhadap pengendali pencampur kripto Blender dan Sinbad dalam kes pengubahan wang haram.",
            "url": "https://cryptopanic.com/news/click/20534676/"
        },
        {
            "title": "Biro Perlindungan Kewangan Pengguna Cadangkan Keperluan Pengembalian Wang Selepas Kecurian Crypto: Laporan",
            "url": "https://cryptopanic.com/news/click/20534672/"
        },
        {
            "title": "'Microsoft akan mengambil tindakan tegas terhadap penyalahgunaan AI generatif oleh penjenayah'",
            "url": "https://cryptopanic.com/news/click/20534668/"
        },
        {
            "title": "Adakah Penurunan 30% Dogecoin Peluang Untuk Membeli Dengan Diskaun? Ini Adalah Tahap Penting Untuk Diperhatikan.",
            "url": "https://cryptopanic.com/news/click/20534648/"
        },
        {
            "title": "'Pengilang Yang Diperdagangkan Secara Awam Ini Melancarkan Simpanan Perbendaharaan Bitcoin'",
            "url": "https://cryptopanic.com/news/click/20534644/"
        },
        {
            "title": "\"Kenya Bersiap untuk Menghalalkan Kriptowang: Laporan\"",
            "url": "https://cryptopanic.com/news/click/20534930/"
        }
    ]
}